roliwrapper/__init__.py
roliwrapper/ad.py
roliwrapper/item.py
roliwrapper/itemapi.py
roliwrapper/player.py
roliwrapper/playerapi.py
roliwrapper/session.py
roliwrapper/tradeads.py
roliwrapper-2.1.0.dist-info/METADATA
roliwrapper-2.1.0.dist-info/WHEEL
roliwrapper-2.1.0.dist-info/top_level.txt
roliwrapper-2.1.0.dist-info/RECORD
