Metadata-Version: 2.1
Name: roliwrapper
Version: 2.1.0
Summary: Rolimons API Wrapper
Home-page: https://github.com/htach/roliwrapper
Author: htach
Requires-Python: >=3.9
Requires-Dist: requests
